my_python_package24/__init__.py
my_python_package24/helloworld.py
my_python_package24-1.0.1.dist-info/LICENSE
my_python_package24-1.0.1.dist-info/METADATA
my_python_package24-1.0.1.dist-info/WHEEL
my_python_package24-1.0.1.dist-info/top_level.txt
my_python_package24-1.0.1.dist-info/RECORD
