Metadata-Version: 2.1
Name: my_python_package24
Version: 1.0.1
Home-page: https://github.com/nirmalkahirwar/my_python_package24
Author: Lamrin
Author-email: ahirwarnirmal2017@gmail.com
Classifier: Programming Language :: Python :: 3
Classifier: License :: OSI Approved :: MIT License
Classifier: Operating System :: OS Independent
Requires-Python: >=3.6
License-File: LICENSE
Requires-Dist: numpy
Requires-Dist: pandas
Requires-Dist: scikit-learn
